Metadata-Version: 2.1
Name: apiflash-client
Version: 0.2
Summary: ApiFlash.com Client
Home-page: https://github.com/fictivekin/apiflash-client
Author: Fictive Kin LLC
Author-email: hello@fictivekin.com
Maintainer: Fictive Kin LLC
Maintainer-email: hello@fictivekin.com
License: MIT
Classifier: Development Status :: 3 - Alpha
Classifier: License :: OSI Approved :: MIT License
Classifier: Programming Language :: Python :: 3.7
Classifier: Programming Language :: Python :: 3.8
Classifier: Programming Language :: Python :: 3.9
Classifier: Programming Language :: Python :: 3.10
Classifier: Programming Language :: Python :: 3.11
Classifier: Topic :: Software Development
Requires-Python: >=3.7
License-File: LICENCE.txt
